<?xml version="1.0" encoding="UTF-8"?>
<!DOCTYPE suite SYSTEM "http://testng.org/testng-1.0.dtd">
<suite name="AssessmentCandidate suite" parallel="tests" thread-count="5">
<!--  <listeners>
<listener class-name="com.test.automation.UIAutomation.customListener.Listener"></listener>
 <listener class-name="com.test.automation.UIAutomation.customListener.RetryListener"></listener>
</listeners> -->
  <test name="AssessmentCandidate">
    <classes>
      <class name="com.test.automation.UIAutomation.tests.AssessmentCandidateTest"/>
    </classes>
  </test> <!-- Test -->
</suite> <!-- Suite -->
